okta_aws_cred_helper/__init__.py
okta_aws_cred_helper/helper.py
okta_aws_cred_helper/data/__init__.py
okta_aws_cred_helper/data/data.yaml
okta_aws_credential_helper-0.3.2.dist-info/LICENSE.txt
okta_aws_credential_helper-0.3.2.dist-info/METADATA
okta_aws_credential_helper-0.3.2.dist-info/WHEEL
okta_aws_credential_helper-0.3.2.dist-info/entry_points.txt
okta_aws_credential_helper-0.3.2.dist-info/top_level.txt
okta_aws_credential_helper-0.3.2.dist-info/RECORD
