Metadata-Version: 2.1
Name: okta-aws-credential-helper
Version: 0.3.2
Summary: Okta AWS SAML credential helper
Home-page: https://github.com/cheney-yan/aws-okta-credential-helper
Author: Cheney Yan
Author-email: cheney.yan@gmail.com
License: UNKNOWN
Keywords: Okta AWS SAML Credential Helper
Platform: UNKNOWN
Classifier: Development Status :: 5 - Production/Stable
Classifier: Intended Audience :: Developers
Classifier: Topic :: Software Development :: Build Tools
Classifier: License :: OSI Approved :: MIT License
Classifier: Programming Language :: Python :: 3
Requires-Python: >=3.0.0
Requires-Dist: boto3
Requires-Dist: click (==7.0)
Requires-Dist: click-log (==0.3.2)
Requires-Dist: sh
Requires-Dist: keyring
Requires-Dist: python-dateutil
Requires-Dist: bs4
Requires-Dist: simplejson
Requires-Dist: requests[security]
Requires-Dist: pyyaml
